paaaaath/__init__.py
paaaaath/blob.py
paaaaath/common.py
paaaaath/gcs.py
paaaaath/http.py
paaaaath/posix.py
paaaaath/s3.py
paaaaath/uri.py
paaaaath/windows.py
paaaaath-0.2.7.dist-info/LICENSE
paaaaath-0.2.7.dist-info/METADATA
paaaaath-0.2.7.dist-info/WHEEL
paaaaath-0.2.7.dist-info/RECORD
