Metadata-Version: 2.1
Name: paaaaath
Version: 0.2.7
Summary: a useful alternative Path object
Home-page: https://github.com/ar90n/paaaaath
License: MIT
Keywords: path,s3,gcs,cloud
Author: Masahiro Wada
Author-email: argon.argon.argon@gmail.com
Requires-Python: >=3.7,<3.11
Classifier: License :: OSI Approved :: MIT License
Classifier: Programming Language :: Python :: 3
Classifier: Programming Language :: Python :: 3.7
Classifier: Programming Language :: Python :: 3.8
Classifier: Programming Language :: Python :: 3.9
Classifier: Programming Language :: Python :: 3.10
Provides-Extra: all
Provides-Extra: gcs
Provides-Extra: http
Provides-Extra: s3
Requires-Dist: boto3 (>=1.17.36,<2.0.0) ; extra == "s3" or extra == "all"
Requires-Dist: google-cloud-storage (>=1.36.2,<2.0.0) ; extra == "gcs" or extra == "all"
Requires-Dist: importlib_metadata (>=3.7,<4.0) ; python_version >= "3.7" and python_version < "3.8"
Requires-Dist: requests (>=2.25.1,<3.0.0) ; extra == "http" or extra == "all"
Requires-Dist: smart-open (>=5.0,<6.0)
Project-URL: Repository, https://github.com/ar90n/paaaaath
